{
  "player_profile": {
    "account_name": "Ankston",
    "player_level": 58,
    "player_power": 1.23M,
    "spending_level": "low_spender",
    "play_style": "daily_player",
    "clan_boss_difficulty": "nightmare",
    "arena_tier": "gold_4",
    "current_focus": {
      "primary": "",
      "secondary": "",
      "struggling_with": []
    }
  },
  "progression_status": {
    "campaign": {
      "normal": "completed",
      "hard": "completed",
      "brutal": "completed",
      "nightmare": "completed"
    },
    "dungeons": {
      "dragon": {
        "highest_stage": 25,
        "farm_stage": 25,
        "average_time": "4:50",
        "success_rate": 100
      },
      "spider": {
        "highest_stage": 20,
        "farm_stage": 20,
        "average_time": "4:00",
        "success_rate": 100
      },
      "fire_knight": {
        "highest_stage": 25,
        "farm_stage": 25,
        "average_time": "4:50",
        "success_rate": 100
      },
      "ice_golem": {
        "highest_stage": 22,
        "farm_stage": 21,
        "average_time": "5:30",
        "success_rate": 100
      }
    },
    "doom_tower": {
      "normal": {
        "current_floor": 90,
        "highest_floor": 120,
        "secret_rooms_completed": []
      },
      "hard": {
        "current_floor": 0,
        "highest_floor": 12,
        "secret_rooms_completed": []
      }
    },
    "faction_wars": {
      "completed_factions": [],
      "stars_earned": {"normal": 324,},
      "struggling_factions": []
    },
    "hydra": {
      "normal": {
        "weekly_damage": 0,
        "chest_level": "none|basic|advanced|ultimate|mythic"
      },
      "hard": {
        "weekly_damage": 0,
        "chest_level": "none"
      },
      "brutal": {
        "weekly_damage": 0,
        "chest_level": "none"
      },
      "nightmare": {
        "weekly_damage": 0,
        "chest_level": "none"
      }
    }
  },
  "current_resources": {
    "silver": 6190000,
    "gems": 1047,
    "energy": 1304,
    "clan_boss_keys": 1,
    "arena_tokens": 10,
    "tag_arena_tokens": 10,
    "shards": {
      "mystery": 944,
      "ancient": 2,
      "void": 0,
      "sacred": 0,
      "primal": 0
    },
    "books": {
      "legendary": 0,
      "epic": 4,
      "rare": 0
    },
    "potions": {
      "magic": {
        "lesser": 62,
        "greater": 13,
        "superior": 69
      },
      "force": {
        "lesser": 443,
        "greater": 127,
        "superior": 49
      },
      "spirit": {
        "lesser": 88,
        "greater": 3,
        "superior": 13
      },
      "void": {
        "lesser": 379,
        "greater": 204,
        "superior": 39
      }
    },
    "chickens": {
      "rank_6": 0,
      "rank_5": 0,
      "rank_4": 0,
      "rank_3": 0
    },
    "glyphs": {
      "rank_1": 0,
      "rank_2": 0,
      "rank_3": 0,
      "rank_4": 0,
      "rank_5": 0,
      "rank_6": 0
    }
  }
}
